README.md
setup.py
rese/__coconut__.py
rese/__init__.py
rese/sunamount.coco
rese/sunamount.py
rese.egg-info/PKG-INFO
rese.egg-info/SOURCES.txt
rese.egg-info/dependency_links.txt
rese.egg-info/not-zip-safe
rese.egg-info/requires.txt
rese.egg-info/top_level.txt
rese/../LICENSE
rese/../README.md
rese/../sunamount.md