Metadata-Version: 1.2
Name: rese
Version: 2018.1626.2156
Summary: RESE - Real estate sunlight estimator
Home-page: http://github.com/ArneBachmann/realestate-sunamount
Author: Arne Bachmann
Author-email: ArneBachmann@users.noreply.github.com
Maintainer: Arne Bachmann
Maintainer-email: ArneBachmann@users.noreply.github.com
License: Mozilla Public License Version 2.0 (MPL-2.0)
Keywords: real estate solar irradiation sunlight sun amount wattage house room floor window obstacle
Platform: UNKNOWN
Classifier: Development Status :: 5 - Production/Stable
Classifier: Intended Audience :: Developers
Classifier: Intended Audience :: Financial and Insurance Industry
Classifier: Intended Audience :: Other Audience
Classifier: Intended Audience :: Science/Research
Classifier: License :: OSI Approved :: GNU General Public License v3 (GPLv3)
Classifier: Operating System :: OS Independent
Classifier: Programming Language :: Python
Classifier: Programming Language :: Python :: 3
Classifier: Programming Language :: Python :: 3.4
Classifier: Programming Language :: Python :: 3.5
Classifier: Programming Language :: Python :: 3.6
Requires-Python: >=3.0
